allPrint.py
allPrint-1.1.dist-info/LICENSE
allPrint-1.1.dist-info/METADATA
allPrint-1.1.dist-info/WHEEL
allPrint-1.1.dist-info/top_level.txt
allPrint-1.1.dist-info/RECORD
