Metadata-Version: 2.1
Name: allPrint
Version: 1.1
Summary: priiiiiiiiiiiiiiiiiiiiiiiiiiiiiiint
Author: snailBoy
Project-URL: Homepage, https://github.com/sna1lBoy/allPrint
Project-URL: Issues, https://www.youtube.com/watch?v=XGxIE1hr0w4&pp=ygUjcmljayBhc3RsZXkgbmV2ZXIgZ29ubmEgZ2l2ZSB5b3UgdXA%3D
Classifier: Programming Language :: Python :: 3
Classifier: License :: OSI Approved :: MIT License
Classifier: Operating System :: OS Independent
Requires-Python: >=3.8
License-File: LICENSE
